<mujoco>
   <asset>
<texture type="skybox" builtin="gradient" rgb1="0.2 0.1 0.9" rgb2="0.1 0.8 0.6" width="256" height="256"/>
<texture name="flat_0" builtin="flat" rgb1="0.4 0.1 1.0" rgb2="0.4 0.1 1.0"  width="200" height="200"/>
<texture name="gradient_1" builtin="gradient" rgb1="0.2 0.3 0.0" rgb2="0.2 0.8 0.3" width="200" height="200"/>
<texture name="flat_2" builtin="flat" rgb1="0.3 0.4 0.9" rgb2="0.3 0.4 0.9"  width="200" height="200"/>
<texture name="checker_3" builtin="checker" rgb1="0.7 0.6 0.3" rgb2="0.4 0.4 1.0" width="200" height="200"/>
<texture name="gradient_4" builtin="gradient" rgb1="0.2 0.4 0.3" rgb2="0.1 0.7 0.6" width="200" height="200"/>
<texture name="checker_5" builtin="checker" rgb1="0.3 0.7 0.3" rgb2="0.4 0.5 0.4" width="200" height="200"/><material name="flat_0_mat" reflectance="0" texture="flat_0" texuniform="true"/>
<material name="gradient_1_mat" reflectance="0" texture="gradient_1" texuniform="true"/>
<material name="flat_2_mat" reflectance="0" texture="flat_2" texuniform="true"/>
<material name="checker_3_mat" reflectance="0" texrepeat="5 5" texture="checker_3" texuniform="false" />
<material name="gradient_4_mat" reflectance="0" texture="gradient_4" texuniform="true"/>
<material name="checker_5_mat" reflectance="0" texrepeat="8 8" texture="checker_5" texuniform="false" />
   </asset>

   <worldbody>
      <light diffuse=".9 .9 .9" pos="0 0 3" dir="0 0 -1"/>
     <geom type="plane" size="1 1 0.1" rgba="0.3 1.0 0.8 1"/>
<geom type="sphere" pos="0.43 0.69 0.18" size="0.18 0.18 0.18" material="flat_0_mat" euler="0 0 82" />
<geom type="box" pos="-0.58 0.78 0.15" size="0.18 0.15 0.15" material="gradient_1_mat" euler="0 0 31" />
<geom type="box" pos="0.85 -0.16 0.1" size="0.11 0.1 0.1" material="flat_2_mat" euler="0 0 10" />
<geom type="box" pos="-0.34 0.45 0.11" size="0.19 0.16 0.11" material="checker_3_mat" euler="0 0 43" />
<geom type="cylinder" pos="-0.25 0.07 0.2" size="0.18 0.2 0.2" material="gradient_4_mat" euler="0 0 70" />
<geom type="box" pos="-0.01 -0.48 0.14" size="0.17 0.16 0.14" material="checker_5_mat" euler="0 0 64" /><camera euler="60 0 180" fovy="60" name="camera1" pos="-0.2 -1.5 1"></camera>   </worldbody>
</mujoco>