{
    "camera_data": {
        "camera_look_at": {
            "at": [
                1.0,
                0.0,
                0.0
            ],
            "eye": [
                -0.30000001192092896,
                0.0,
                0.0
            ],
            "up": [
                0.0,
                0.0,
                1.0
            ]
        },
        "camera_view_matrix": [
            [
                0.0,
                0.0,
                1.0,
                0.0
            ],
            [
                -1.0,
                0.0,
                0.0,
                0.0
            ],
            [
                0.0,
                -1.0,
                0.0,
                0.0
            ],
            [
                0.0,
                0.0,
                0.30000001192092896,
                1.0
            ]
        ],
        "height": 761,
        "intrinsics": {
            "cx": 358.0,
            "cy": 380.5,
            "fx": 189.840087890625,
            "fy": 189.840087890625
        },
        "location_worldframe": [
            -0.30000001192092896,
            0.0,
            -0.0
        ],
        "quaternion_xyzw_worldframe": [
            -0.5,
            0.5,
            -0.5,
            0.5
        ],
        "width": 716
    },
    "objects": [
        {
            "bounding_box_minx_maxx_miny_maxy": [
                420,
                431,
                396,
                443
            ],
            "class": "zuvacky",
            "local_cuboid": null,
            "local_to_world_matrix": [
                [
                    0.4645805358886719,
                    0.40248799324035645,
                    -7.976351737976074,
                    -0.0
                ],
                [
                    -2.359222650527954,
                    -7.626358509063721,
                    -0.5222397446632385,
                    0.0
                ],
                [
                    -7.630087852478027,
                    2.3825762271881104,
                    -0.32418733835220337,
                    -0.0
                ],
                [
                    1.6085948944091797,
                    -0.6698698401451111,
                    -0.42163097858428955,
                    1.0
                ]
            ],
            "location": [
                0.6698698401451111,
                0.42163097858428955,
                1.9085948467254639
            ],
            "location_worldframe": [
                1.6085948944091797,
                -0.6698698401451111,
                -0.42163097858428955
            ],
            "name": "hope_zuvacky_0",
            "projected_cuboid": [
                [
                    419.1596620082855,
                    452.1072412133217
                ],
                [
                    423.06596636772156,
                    396.78601586818695
                ],
                [
                    431.96995210647583,
                    397.5449649095535
                ],
                [
                    427.8594386577606,
                    453.5667620897293
                ],
                [
                    419.0450744628906,
                    445.5283976793289
                ],
                [
                    422.61977910995483,
                    394.77261459827423
                ],
                [
                    430.7577567100525,
                    395.4425236582756
                ],
                [
                    427.01204562187195,
                    446.7874765396118
                ],
                [
                    425.1299078464508,
                    422.9385507106781
                ]
            ],
            "provenance": "nvisii",
            "px_count_all": 0,
            "px_count_visib": 0,
            "quaternion_xyzw": [
                1.961398720741272,
                2.115889549255371,
                -0.9005374312400818,
                0.10834312438964844
            ],
            "quaternion_xyzw_worldframe": [
                1.5342038869857788,
                -0.3188517987728119,
                -2.5430843830108643,
                -0.47334253787994385
            ],
            "segmentation_id": 1,
            "visibility": 1
        },
        {
            "bounding_box_minx_maxx_miny_maxy": [
                275,
                360,
                369,
                407
            ],
            "class": "lentilky",
            "local_cuboid": null,
            "local_to_world_matrix": [
                [
                    -5.748444080352783,
                    5.338948726654053,
                    -1.5655732154846191,
                    -0.0
                ],
                [
                    5.4722490310668945,
                    5.8320441246032715,
                    -0.20435458421707153,
                    -0.0
                ],
                [
                    1.0049316883087158,
                    -1.2177408933639526,
                    -7.842653274536133,
                    -0.0
                ],
                [
                    1.4532926082611084,
                    0.32198235392570496,
                    -0.034407973289489746,
                    1.0
                ]
            ],
            "location": [
                -0.32198235392570496,
                0.034407973289489746,
                1.7532925605773926
            ],
            "location_worldframe": [
                1.4532926082611084,
                0.32198235392570496,
                -0.034407973289489746
            ],
            "name": "hope_lentilky_1",
            "projected_cuboid": [
                [
                    289.9761172533035,
                    407.35927551984787
                ],
                [
                    360.6466522216797,
                    384.82785111665726
                ],
                [
                    348.99126374721527,
                    385.01382356882095
                ],
                [
                    279.49692618846893,
                    405.85008639097214
                ],
                [
                    285.24305415153503,
                    384.2907082438469
                ],
                [
                    358.08838391304016,
                    368.2395846545696
                ],
                [
                    346.4570652246475,
                    369.383088439703
                ],
                [
                    274.9870420694351,
                    384.59257328510284
                ],
                [
                    323.6376277208328,
                    384.72624665498734
                ]
            ],
            "provenance": "nvisii",
            "px_count_all": 0,
            "px_count_visib": 0,
            "quaternion_xyzw": [
                -0.3108596205711365,
                1.6643403768539429,
                1.7913994789123535,
                0.7525975108146667
            ],
            "quaternion_xyzw_worldframe": [
                1.1961413621902466,
                2.25959849357605,
                -0.157339408993721,
                0.2843984067440033
            ],
            "segmentation_id": 2,
            "visibility": 1
        },
        {
            "bounding_box_minx_maxx_miny_maxy": [
                352,
                430,
                433,
                461
            ],
            "class": "lentilky",
            "local_cuboid": null,
            "local_to_world_matrix": [
                [
                    -5.7139153480529785,
                    -5.263188362121582,
                    1.9105029106140137,
                    -0.0
                ],
                [
                    -5.589115619659424,
                    5.525174140930176,
                    -1.494736909866333,
                    0.0
                ],
                [
                    -0.3360973000526428,
                    -2.402352809906006,
                    -7.6233673095703125,
                    0.0
                ],
                [
                    1.5745985507965088,
                    -0.2802811563014984,
                    -0.6362953186035156,
                    1.0
                ]
            ],
            "location": [
                0.2802811563014984,
                0.6362953186035156,
                1.874598503112793
            ],
            "location_worldframe": [
                1.5745985507965088,
                -0.2802811563014984,
                -0.6362953186035156
            ],
            "name": "hope_lentilky_2",
            "projected_cuboid": [
                [
                    431.20513892173767,
                    451.1159626841545
                ],
                [
                    367.42959475517273,
                    449.4053336381912
                ],
                [
                    356.93952107429504,
                    456.3996214866638
                ],
                [
                    421.92785811424255,
                    460.87112498283386
                ],
                [
                    424.8142693042755,
                    431.5538833141327
                ],
                [
                    362.8915011882782,
                    434.8715411424637
                ],
                [
                    352.17293524742126,
                    440.9912141561508
                ],
                [
                    415.06856656074524,
                    439.6909038424492
                ],
                [
                    386.8846821784973,
                    445.4381330013275
                ]
            ],
            "provenance": "nvisii",
            "px_count_all": 0,
            "px_count_visib": 0,
            "quaternion_xyzw": [
                -1.6303579807281494,
                0.850053608417511,
                0.16079407930374146,
                1.8155261278152466
            ],
            "quaternion_xyzw_worldframe": [
                -1.2175182104110718,
                2.228365898132324,
                -0.43721386790275574,
                -0.2520456910133362
            ],
            "segmentation_id": 3,
            "visibility": 1
        },
        {
            "bounding_box_minx_maxx_miny_maxy": [
                355,
                420,
                399,
                433
            ],
            "class": "lentilky",
            "local_cuboid": null,
            "local_to_world_matrix": [
                [
                    -0.05029740184545517,
                    7.512729644775391,
                    2.7488901615142822,
                    -0.0
                ],
                [
                    -5.1308393478393555,
                    -2.139378786087036,
                    5.753049850463867,
                    0.0
                ],
                [
                    6.137750625610352,
                    -1.7268444299697876,
                    4.831774711608887,
                    -0.0
                ],
                [
                    1.8486109972000122,
                    -0.3772621750831604,
                    -0.44897279143333435,
                    1.0
                ]
            ],
            "location": [
                0.3772621750831604,
                0.44897279143333435,
                2.148611068725586
            ],
            "location_worldframe": [
                1.8486109972000122,
                -0.3772621750831604,
                -0.44897279143333435
            ],
            "name": "hope_lentilky_3",
            "projected_cuboid": [
                [
                    358.2571711540222,
                    407.9006821513176
                ],
                [
                    420.9463315010071,
                    430.7788317799568
                ],
                [
                    428.33874320983887,
                    422.2650129199028
                ],
                [
                    362.38646245002747,
                    398.16983234882355
                ],
                [
                    354.8637367486954,
                    419.0537676215172
                ],
                [
                    421.5164098739624,
                    443.34925413131714
                ],
                [
                    429.4329369068146,
                    434.9682921767235
                ],
                [
                    359.0793421268463,
                    409.29574769735336
                ],
                [
                    391.83362650871277,
                    420.669550716877
                ]
            ],
            "provenance": "nvisii",
            "px_count_all": 0,
            "px_count_visib": 0,
            "quaternion_xyzw": [
                0.8370256423950195,
                -0.6842851042747498,
                2.963921070098877,
                -0.021036267280578613
            ],
            "quaternion_xyzw_worldframe": [
                1.568848967552185,
                0.7107869982719421,
                1.4161083698272705,
                2.232097864151001
            ],
            "segmentation_id": 4,
            "visibility": 1
        },
        {
            "bounding_box_minx_maxx_miny_maxy": [
                388,
                431,
                352,
                430
            ],
            "class": "pez",
            "local_cuboid": null,
            "local_to_world_matrix": [
                [
                    -5.619415760040283,
                    2.3369274139404297,
                    -5.192391395568848,
                    0.0
                ],
                [
                    -0.11250017583370209,
                    7.248196125030518,
                    3.3839309215545654,
                    0.0
                ],
                [
                    5.692934989929199,
                    2.4499826431274414,
                    -5.058465480804443,
                    -0.0
                ],
                [
                    1.5596957206726074,
                    -0.5131731033325195,
                    -0.0773811861872673,
                    1.0
                ]
            ],
            "location": [
                0.5131731033325195,
                0.0773811861872673,
                1.8596956729888916
            ],
            "location_worldframe": [
                1.5596957206726074,
                -0.5131731033325195,
                -0.0773811861872673
            ],
            "name": "hope_pez_4",
            "projected_cuboid": [
                [
                    403.5300061702728,
                    430.3739107847214
                ],
                [
                    410.56828474998474,
                    383.72993326187134
                ],
                [
                    398.36477518081665,
                    378.01089480519295
                ],
                [
                    388.1182587146759,
                    423.21451568603516
                ],
                [
                    429.96217346191406,
                    405.4890276789665
                ],
                [
                    431.761816740036,
                    357.43671706318855
                ],
                [
                    417.6471917629242,
                    350.78001457452774
                ],
                [
                    411.37142181396484,
                    396.7960855960846
                ],
                [
                    410.886057138443,
                    388.8998313546181
                ]
            ],
            "provenance": "nvisii",
            "px_count_all": 0,
            "px_count_visib": 0,
            "quaternion_xyzw": [
                -0.6694905757904053,
                0.2546461820602417,
                2.1762163639068604,
                1.2500578165054321
            ],
            "quaternion_xyzw_worldframe": [
                0.2556571364402771,
                2.1752054691314697,
                0.6705014705657959,
                1.2510687112808228
            ],
            "segmentation_id": 5,
            "visibility": 1
        }
    ]
}